geckoterminal_api/__init__.py
geckoterminal_api/api.py
geckoterminal_api/async_api.py
geckoterminal_api/exceptions.py
geckoterminal_api/limits.py
geckoterminal_api/validation.py
geckoterminal_api-0.9.0.dist-info/METADATA
geckoterminal_api-0.9.0.dist-info/WHEEL
geckoterminal_api-0.9.0.dist-info/licenses/LICENSE.md
geckoterminal_api-0.9.0.dist-info/RECORD
