Metadata-Version: 2.3
Name: geckoterminal-api
Version: 0.9.0
Summary: RESTful (sync + async) Python client for GeckoTerminal API
Author-email: Dinesh Pinto <annual.fallout_0z@icloud.com>
License: MIT
Keywords: api,async,bitcoin,coingecko,cryptocurrency,ethereum,geckoterminal,rest,solana
Requires-Python: >=3.10
Requires-Dist: aiohttp>=3.11.7
Requires-Dist: requests>=2.32.3
